bodo_azurefs_sas_token_provider/__init__.py
bodo_azurefs_sas_token_provider/jars/bodo-azurefs-sas-token-provider.jar
bodo_azurefs_sas_token_provider/jars/libs/accessors-smart-2.4.7.jar
bodo_azurefs_sas_token_provider/jars/libs/activation-1.1.jar
bodo_azurefs_sas_token_provider/jars/libs/animal-sniffer-annotations-1.17.jar
bodo_azurefs_sas_token_provider/jars/libs/asm-9.1.jar
bodo_azurefs_sas_token_provider/jars/libs/audience-annotations-0.5.0.jar
bodo_azurefs_sas_token_provider/jars/libs/avro-1.7.7.jar
bodo_azurefs_sas_token_provider/jars/libs/azure-keyvault-core-1.0.0.jar
bodo_azurefs_sas_token_provider/jars/libs/azure-storage-7.0.1.jar
bodo_azurefs_sas_token_provider/jars/libs/checker-qual-2.5.2.jar
bodo_azurefs_sas_token_provider/jars/libs/commons-beanutils-1.9.4.jar
bodo_azurefs_sas_token_provider/jars/libs/commons-cli-1.2.jar
bodo_azurefs_sas_token_provider/jars/libs/commons-codec-1.11.jar
bodo_azurefs_sas_token_provider/jars/libs/commons-collections-3.2.2.jar
bodo_azurefs_sas_token_provider/jars/libs/commons-compress-1.21.jar
bodo_azurefs_sas_token_provider/jars/libs/commons-configuration2-2.1.1.jar
bodo_azurefs_sas_token_provider/jars/libs/commons-io-2.8.0.jar
bodo_azurefs_sas_token_provider/jars/libs/commons-lang3-3.12.0.jar
bodo_azurefs_sas_token_provider/jars/libs/commons-logging-1.1.3.jar
bodo_azurefs_sas_token_provider/jars/libs/commons-math3-3.1.1.jar
bodo_azurefs_sas_token_provider/jars/libs/commons-net-3.6.jar
bodo_azurefs_sas_token_provider/jars/libs/commons-text-1.4.jar
bodo_azurefs_sas_token_provider/jars/libs/curator-client-4.2.0.jar
bodo_azurefs_sas_token_provider/jars/libs/curator-framework-4.2.0.jar
bodo_azurefs_sas_token_provider/jars/libs/curator-recipes-4.2.0.jar
bodo_azurefs_sas_token_provider/jars/libs/dnsjava-2.1.7.jar
bodo_azurefs_sas_token_provider/jars/libs/failureaccess-1.0.jar
bodo_azurefs_sas_token_provider/jars/libs/gson-2.8.9.jar
bodo_azurefs_sas_token_provider/jars/libs/guava-27.0-jre.jar
bodo_azurefs_sas_token_provider-1.0.dist-info/METADATA
bodo_azurefs_sas_token_provider-1.0.dist-info/WHEEL
bodo_azurefs_sas_token_provider-1.0.dist-info/top_level.txt
bodo_azurefs_sas_token_provider-1.0.dist-info/RECORD
